django_haveli_admin/__init__.py
django_haveli_admin/admin.py
django_haveli_admin/forms.py
django_haveli_admin/sites.py
django_haveli_admin/utils.py
django_haveli_admin/static/admin/css/base.css
django_haveli_admin/static/admin/css/changelists.css
django_haveli_admin/static/admin/css/common.css
django_haveli_admin/static/admin/css/forms.css
django_haveli_admin/static/admin/css/login.css
django_haveli_admin/static/admin/css/widgets.css
django_haveli_admin/static/admin/js/haveli.init.js
django_haveli_admin/static/admin/js/haveli_filter.js
django_haveli_admin/static/admin/js/haveli_sidebar.js
django_haveli_admin/static/admin/js/user_menu.js
django_haveli_admin/static/images/admin.png
django_haveli_admin/static/images/auth_icon.png
django_haveli_admin/static/images/branding.png
django_haveli_admin/static/images/django_haveli_changeform.png
django_haveli_admin/static/images/home.png
django_haveli_admin/templates/admin/base.html
django_haveli_admin/templates/admin/base_site.html
django_haveli_admin/templates/admin/change_list.html
django_haveli_admin/templates/admin/filter.html
django_haveli_admin/templates/admin/login.html
django_haveli_admin/templates/admin/nav_sidebar.html
django_haveli_admin/templates/admin/search_form.html
django_haveli_admin/templates/admin/sidebar_list.html
django_haveli_admin/templates/admin/suit_change_list.html
django_haveli_admin/templates/admin/user_drop_down.html
django_haveli_admin/templatetags/django_template_tags.py
django_haveli_admin/templatetags/haveli_list_filters.py
django_haveli_admin/templatetags/__pycache__/django_template_tags.cpython-37.pyc
django_haveli_admin/templatetags/__pycache__/haveli_list.cpython-37.pyc
django_haveli_admin/templatetags/__pycache__/haveli_list_filters.cpython-37.pyc
django_haveli_admin-0.1.0.dist-info/LICENSE
django_haveli_admin-0.1.0.dist-info/METADATA
django_haveli_admin-0.1.0.dist-info/WHEEL
django_haveli_admin-0.1.0.dist-info/top_level.txt
django_haveli_admin-0.1.0.dist-info/RECORD
