Metadata-Version: 2.1
Name: django-haveli-admin
Version: 0.1.0
Summary: Improved theme for Django admin Interface
Home-page: https://github.com/purnendukar/django-haveli-admin
Author: Purnendu Kar
Author-email: purnendu.kar8@gmail.com
License: BSD License
Platform: UNKNOWN
Classifier: Development Status :: 5 - Production/Stable
Classifier: Environment :: Web Environment
Classifier: Framework :: Django
Classifier: Intended Audience :: Developers
Classifier: Intended Audience :: System Administrators
Classifier: License :: OSI Approved :: BSD License
Classifier: Operating System :: OS Independent
Classifier: Programming Language :: Python
Classifier: Topic :: Software Development
Classifier: Topic :: Software Development :: User Interfaces
Classifier: Operating System :: OS Independent
